envisolation/__init__.py
envisolation/model_executor.py
env_isolation-0.8.0.dist-info/LICENSE
env_isolation-0.8.0.dist-info/METADATA
env_isolation-0.8.0.dist-info/WHEEL
env_isolation-0.8.0.dist-info/top_level.txt
env_isolation-0.8.0.dist-info/RECORD
